django_epfl_mail-2.2.0.dist-info/METADATA
django_epfl_mail-2.2.0.dist-info/WHEEL
django_epfl_mail-2.2.0.dist-info/entry_points.txt
django_epflmail/__init__.py
django_epflmail/locale/de/LC_MESSAGES/django.mo
django_epflmail/locale/de/LC_MESSAGES/django.po
django_epflmail/locale/en/LC_MESSAGES/django.mo
django_epflmail/locale/en/LC_MESSAGES/django.po
django_epflmail/locale/fr/LC_MESSAGES/django.mo
django_epflmail/locale/fr/LC_MESSAGES/django.po
django_epflmail/templates/epflmail/base.html
django_epflmail/templates/epflmail/default.html
django_epflmail/templates/epflmail/includes/app-title.inc.html
django_epflmail/templates/epflmail/includes/copyright.inc.html
django_epflmail/templates/epflmail/includes/header.inc.html
django_epflmail/templates/epflmail/includes/logo.inc.html
django_epflmail/templates/epflmail/includes/online.inc.html
django_epflmail/templates/epflmail/includes/spacer.inc.html
django_epflmail/templates/epflmail/includes/style.inc.html
django_epfl_mail-2.2.0.dist-info/RECORD
