Metadata-Version: 2.1
Name: django-epfl-mail
Version: 2.2.0
Summary: A Django application with templates for emails.
Author-Email: William Belle <william.belle@gmail.com>
License: MIT
Classifier: Environment :: Web Environment
Classifier: Framework :: Django
Classifier: Framework :: Django :: 2.2
Classifier: Framework :: Django :: 3.2
Classifier: Framework :: Django :: 4.2
Classifier: Framework :: Django :: 5.2
Classifier: Intended Audience :: Developers
Classifier: Operating System :: OS Independent
Classifier: Programming Language :: Python
Classifier: Programming Language :: Python :: 3
Classifier: Programming Language :: Python :: 3.7
Classifier: Programming Language :: Python :: 3.8
Classifier: Programming Language :: Python :: 3.9
Classifier: Programming Language :: Python :: 3.10
Classifier: Programming Language :: Python :: 3.11
Classifier: Programming Language :: Python :: 3.12
Classifier: Programming Language :: Python :: 3.13
Classifier: Programming Language :: Python :: 3.14
Project-URL: Homepage, https://github.com/epfl-si/django-epfl-mail
Project-URL: Source, https://github.com/epfl-si/django-epfl-mail
Project-URL: Tracker, https://github.com/epfl-si/django-epfl-mail/issues
Project-URL: Changelog, https://github.com/epfl-si/django-epfl-mail/blob/main/CHANGELOG.md
Requires-Python: >=3.7
Requires-Dist: django>=2.2
